{
  "title":"\"例のフォント\"変換ツール",
  "paragraph":["00$script","0$h3","1$p","2$h3","3$div$info_warn","4$div$info_notice","5$h3","6$p","7$div$$background:var(--d232327lf9f9fa);","8$h3","10$div$$overflow:auto;$result","11$div","12$h3","13$table","14$h3","15$p","16$p"],
  "00$script":"works/1669302000/script_1669302000.js",
  "0$h3":"仕様",
  "1$p":"入力された文字列をTIMS/TIS/TIOS/S-TIMなどのモニタ表示器で使用されている&quot;例のフォント&quot;で表示します。<br>現在の対応文字数:884文字 (2024/2/10現在)",
  "2$h3":"注意事項・お知らせ",
  "3$div$info_warn":"このページで使用しているコードは個人が趣味の範囲で作成したものです。誤動作等によって生じた損害については一切責任を負いかねます。<br>また、各種権利の関係で公開を停止することがあります。",
  "4$div$info_notice":"本ツールで使用している字形に誤りなどを見つけた場合や現在未対応の文字の資料をお持ちの場合はDMなどでお知らせください。",
  "5$h3":"文字列入力・文字色設定",
  "6$p":"表示させたい文字列、および文字色を設定して下さい。",
  "7$div$$background:var(--d232327lf9f9fa);":"<img src='works/1669302000/img1.png' id='sourceImage' class='hidden'><textarea id='textInput' rows='4'>Type here</textarea><br><input type='color' id='textColor' value='#ffffff' onchange='_1669302000_colorchange()'><label for='textColor' id='colorDisplay'>#ffffff</label><br><input type='button' id='runbutton' value='変換' style='vertical-align:3px;' onclick='_1669302000_run()'>",
  "8$h3":"変換結果",
  "10$div$$overflow:auto;$result":"<canvas id='imageOutput' width='300' height='300'></canvas>",
  "11$div":"<div class='info_warn hidden' id='errorInfo'></div>",
  "12$h3":"更新・修正情報",
  "13$table":[["th$日付","th$追加$min-width:100px;","th$修正$min-width:100px;","th$その他$min-width:100px;"],["td$2022/12/04","td$天(U+5929), 比(U+6BD4), 祐(U+7950), 脱(U+8131)","td$寺(U+5BFA)","td$"],["td$2023/01/18","td$f(U+66), 〜(U+301C), 久(U+4E45), 喜(U+559C), 完(U+5B8C), 糸(U+7CF8), 錦(U+9326)","td$","td$"],["td$2023/02/15","td$₂(U+2082), か(U+304B), ん(U+3093), ボ(U+30DC), 佐(U+4F50), 布(U+5E03), 庄(U+5E84), 当(U+5F53), 担(U+62C5), 操(U+64CD), ･(U+FF65)","td$","td$"],["td$2023/03/19","td$ざ(U+3056), ザ(U+30B6), 倉(U+5009), 岡(U+5CA1), 星(U+661F), 板(U+677F), 永(U+6C38), 浅(U+6D45), 片(U+7247), 由(U+7531), 窪(U+7AAA), 羽(U+7FBD), 草(U+8349), 荻(U+837B), 賀(U+8CC0), 踊(U+8E0A), 近(U+8FD1), 随(U+968F), ＜(U+FF1C), ＞(U+FF1E)","td$","td$"],["td$2023/04/30","td$ズ(U+30BA), ヒ(U+30D2), 俣(U+4FE3), 君(U+541B), 塩(U+5869), 富(U+5BCC), 楽(U+697D), 沼(U+6CBC), 津(U+6D25), 舞(U+821E), 虎(U+864E), 逗(U+9017), 銀(U+9280), 須(U+9808)","td$賀(U+8CC0)","td$"],["td$2023/07/02","td$な(U+306A), 丸(U+4E38), 反(U+53CD), 妙(U+5999), 巣(U+5DE3), 幸(U+5E78), 役(U+5F79), 志(U+5FD7), 村(U+6751), 根(U+6839), 求(U+6C42), 洗(U+6D17), 綱(U+7DB1), 芝(U+829D), 蓮(U+84EE), 要(U+8981), 読(U+8AAD), 鴨(U+9D28)","td$","td$<a href='https://www.twitter.com/TINV_6'>૮(@TINV_6)</a>様提供"],["td$2023/08/27","td$ツ(U+30C4), ナ(U+30CA), 十(U+5341), 固(U+56FA), 境(U+5883), 峰(U+5CF0), 崎(U+5D0E), 広(U+5E83), 淵(U+6DF5), 溜(U+6E9C), 煙(U+7159), 王(U+738B), 赤(U+8D64), 鶴(U+9DB4), 麻(U+9EBB)","td$三(U+4E09), 示(U+793A), 羽(U+7FBD)","td$一部字形は<a href='https://www.twitter.com/BVE_i_'>BVE_I_🐧⚡(@BVE_i_)</a>様提供"],["td$2023/12/31","td$ず(U+305A), め(U+3081), ゆ(U+3086), 万(U+4E07), 希(U+5E0C), 弥(U+5F25), 徳(U+5FB3), 望(U+671B), 緑(U+7DD1), 騎(U+9A0E)","td$","td$<a href='https://www.twitter.com/BVE_i_'>BVE_I_🐧⚡(@BVE_i_)</a>様提供"],["td$2024/02/10","td$,(U+2C), v(U+76), 世(U+4e16), 乃(U+4E43), 会(U+4F1A), 堂(U+5802), 売(U+58F2), 幕(U+5E55), 師(U+5E2B), 幡(U+5E61), 張(U+5F35), 括(U+62EC), 斐(U+6590), 梅(U+6885), 歳(U+6B73), 狛(U+72DB), 甲(U+7532), 登(U+767B), 砂(U+7802), 祖(U+7956), 禁(U+7981), 経(U+7D4C), 絡(U+7D61), 習(U+7FD2), 英(U+82F1), 蒲(U+84B2), 誤(U+8AA4), 議(U+8b70), 豊(U+8C4A), 豪(U+8C6A), ｶ(U+FF76)","td$読(U+8AAD)","td$"]],
  "14$h3":"対応文字一覧",
  "15$p":"2024/2/10現在、Unicodeコードポイント順<br>※便宜上、波ダッシュ(Wave Dash,U+301C)と全角チルダ(Fullwidth Tilde,U+FF5E)には同一字形を登録しています。",
  "16$p":" ()+,-./0123456789:<>ABCDEFHIKLMNOPRSTUVZ[]abcdefghijklmnoprstuvy²³¹ō※⁰⁴⁵₀₁₂₃₄₅℃№←→⇩①②◆◇●➡⬅⬆⬇　、。々「」〜あいおかがきくけさざしすずせただちつてでとなにのはばひびまみむめゃゆらりるれわをんアィイウエオカキクグケコサザシスズタチッツテデトドナニネノハバパヒビフブプホボマムメモュラリルレロワンヴヶ・ー一丁万三上下不世丘両中丸乃久乗亀了予事二井京人仕他代令以件伊休会伝位住佐体作促保信俣修倉値停側傘備傾働優元先光入全八公六内再冷処出分切列初別到制刻削前割力加効動務勢勤化北区十千半南単印厚原去参反取受台右号司各合吉名向君告和品員唐喚喜営器回固国園土圧在地坂城域基堀堂報場塚塩境壁士売変外多大天太央失奥女妙始子学孫宇安完定客室宮害宿富審寺専導小履山岡岩峰島崎川巣左市布希師席帯常幕幡平幸広庄度座庫康延引弥弱張強当影役径待後徒御徳志忘応快急性情意態成我戒戸房所扇扉手打扱把抑折択押担拝括指挟挿掃掌接換握揺損携摩操支放故救数整文斐斜断新方施旅日早明星春昼時普暖暗暮更月有望期木末本杉村東松板架柏査栗根案桜梅棒棚検業楽構様標模横橋機次止正武歳歴残比気水永求江池沢河治沼況泉注洗津浅浜浦海消淵混清渋減温湖湘湯湿源準溜滅瀬火灯災点烏無煙照熱片物特状狛狭率玉王現球理瑞生用田由甲町画番異病発登白百目直相省着矢知短石砂確磐磯示祐祖神禁秋秒程種稲稼積空窪端竹第算糸系約細終組経絡給統続綱綾緊総緑線締編緩練置美群羽習老考者耐聞能脱臨自舞航船良色芝英茶草荷荻菊華萩葉蒲蓄蓮蔵藤虎行街表袋装補西要見覧解計記設試詫話詳誌認誘誤読調警議護谷豊豪賀赤起越足距路踊踏身車転輪込近返退送逗通速連進遅遊運過道遠選遺避郎部都里野量金鉄銀錠錦録長門閉開間関防降限除随隔障雑離雪電震霞非面響頃項須領題風飯馬駅駆駐騎験高鴨鶯鶴麗麻黒％（）＊＋－．／０１２３４５６７８９：＜＞ＡＢＣＤＥＦＧＨＩＪＫＭＮＯＰＲＳＴＶＷＹＺｂｋｍ～･ｨｫｭｮｯｰｱｲｵｶｷｸｺｻｼｽｾﾀﾁﾃﾄﾆﾉﾊﾋﾌﾎﾏﾑﾒﾓﾗﾘﾙﾚﾛﾝﾞﾟ￰￱￲￳￴￵￶￷￰￱￲￳￴￵￶￷"
}
